pyebpf/__init__.py
pyebpf/ebpf_wrapper.py
pyebpf/helpers.py
pyebpf/normalizers.py
pyebpf-1.0.4.dist-info/METADATA
pyebpf-1.0.4.dist-info/RECORD
pyebpf-1.0.4.dist-info/WHEEL
pyebpf-1.0.4.dist-info/top_level.txt
