Metadata-Version: 2.1
Name: pyebpf
Version: 1.0.4
Summary: A bcc-based Python eBPF (Extended-Berkeley-Packet-Filter) wrapper
Home-page: https://github.com/dany74q/pyebpf
Author: Danny Shemesh (dany74q)
Author-email: dany74q@gmail.com
License: UNKNOWN
Project-URL: Source, https://github.com/dany74q/pyebpf/
Project-URL: Bug Reports, https://github.com/dany74q/pyebpf/issues
Keywords: bpf ebpf
Platform: UNKNOWN
Classifier: Development Status :: 4 - Beta
Classifier: Intended Audience :: Developers
Classifier: License :: OSI Approved :: MIT License
Classifier: Programming Language :: Python :: 2
Classifier: Programming Language :: Python :: 2.7
Classifier: Programming Language :: Python :: 3
Classifier: Programming Language :: Python :: 3.4
Classifier: Programming Language :: Python :: 3.5
Classifier: Programming Language :: Python :: 3.6
Classifier: Programming Language :: Python :: 3.7
